[
    {
        "local": {
            "nombre": {
                "completo": "UNION ARRUFO",
                "corto": "CUDA"
            },
            "goles": [
                {
                    "min":"",
                    "jugador":"",
                    "penal":false
                }
            ],
            "info": {
                "amarillas": [],
                "rojas_directas": []
            },
            "logo": "cuda.png"
        },
        "visitante": {
            "nombre": {
                "completo": "ATL. TOSTADO",
                "corto": "CAT"
            },
            "goles": [
                {
                    "min":"",
                    "jugador":"",
                    "penal":false
                }
            ],
            "info": {
                "amarillas": [],
                "rojas_directas": []
            },
            "logo": "cat.png"
        },
        "fecha": "09/06/2024 - 15:00hs",
        "estado": "jugando",
        "contexto": []
    },
     
    {
        "local": {
            "nombre": {
                "completo": "ATL. SELVA",
                "corto": "CAS"
            },
            "goles": [
                {
                    "min":"",
                    "jugador":"Facundo Mena",
                    "penal":false
                }
            ],
            "info": {
                "amarillas": [],
                "rojas_directas": []
            },
            "logo": "cas.png"
        },
        "visitante": {
            "nombre": {
                "completo": "ATL. LIBERTAD TRINIDAD",
                "corto": "CALT"
            },
            "goles": [
                {
                    "min":"",
                    "jugador":"Vignolo",
                    "penal":false
                },
                {
                    "min":"",
                    "jugador":"Kevin Muñoz",
                    "penal":true
                }
            ],
            "info": {
                "amarillas": [],
                "rojas_directas": []
            },
            "logo": "calt.png"
        },
        "fecha":"09/06/2024 - 15:00hs",
        "estado": "jugando",
        "contexto": []
    },

    {
        "local": {
            "nombre": {
                "completo": "UNION Y JUVENTUD (B)",
                "corto": "UJB"
            },
            "goles": [
                {
                    "min":"",
                    "jugador":"",
                    "penal":false
                }
            ],
            "info": {
                "amarillas": [],
                "rojas_directas": []
            },
            "logo": "bandera.png"
        },
        "visitante": {
            "nombre": {
                "completo": "CENTRAL ARG. OLÍMPICO",
                "corto": "CCAO"
            },
            "goles": [
                {
                    "min":"",
                    "jugador":"Sayago",
                    "penal":false
                },
                {
                    "min":"",
                    "jugador":"Fernando Romero",
                    "penal":false
                },
                {
                    "min":"",
                    "jugador":"Brian Yulka",
                    "penal":false
                }
            ],
            "info": {
                "amarillas": [],
                "rojas_directas": []
            },
            "logo": "ccao.png"
        },
        "fecha": "09/06/2024 - 15:00hs",
        "estado": "jugando",
        "contexto": []
    },

    {
        "local": {
            "nombre": {
                "completo": "FERRO DHO (SC)",
                "corto": "FDSC"
            },
            "goles": [],
            "info": {
                "amarillas": [],
                "rojas_directas": []
            },
            "logo": "ferro.png"
        },
        "visitante": {
            "nombre": {
                "completo": "SAN LORENZO (A)",
                "corto": "CSLA"
            },
            "goles": [],
            "info": {
                "amarillas": [],
                "rojas_directas": []
            },
            "logo": "ambro.png"
        },
        "fecha": "12/06/2024 - 21:30hs",
        "estado": "Por jugar",
        "contexto": []
    }
]
