[
    {
        "local": {
            "nombre": {
                "completo": "SAN LORENZO (T)",
                "corto": "CSLT"
            },
            "goles": [
                {
                    "min":"",
                    "jugador": "",
                    "penal": false
                }
            ],
            "info": {
                "amarillas": [],
                "rojas_directas": []
            },
            "logo": "slt.png"
        },
        "visitante": {
            "nombre": {
                "completo": "FERRO DHO (SC)",
                "corto": "FDSC"

            },
            "goles": [            ],
            "info": {
                "amarillas": [],
                "rojas_directas": []
            },
            "logo": "ferro.png"
        },
        "fecha": "18/08/2024 - 16:00hs",
        "estado": "jugando",
        "contexto": []
    },

    {
        "local": {
            "nombre": {
                "completo": "UNION ARRUFO",
                "corto": "CUDA"
            },
            "goles": [            ],
            "info": {
                "amarillas": [],
                "rojas_directas": [

                ]
            },
            "logo": "cuda.png"
        },
        "visitante": {
            "nombre": {
                "completo": "ATL. LIBERTAD TRINIDAD",
                "corto": "CALT"

            },
            "goles": [
                {
                    "min": "",
                    "jugador": "Rodrigo Puebla",
                    "penal": false
                },
                {
                    "min": "",
                    "jugador": "Kevin Muñoz",
                    "penal": false
                },
                {
                    "min": "",
                    "jugador": "Daniel Diaz",
                    "penal": false
                }

            ],
            "info": {
                "amarillas": [],
                "rojas_directas": []
            },
            "logo": "calt.png"
        },
        "fecha": "18/08/2024 - 16:00hs",
        "estado": "jugando",
        "contexto": []
    },
    {
        "local": {
            "nombre": {
                "completo": "ATL. UNIÓN DE CERES",
                "corto": "CACU"
            },
            "goles": [
                {
                    "min": "",
                    "jugador": "Andrés Saavedra",
                    "penal": false
                },
                {
                    "min": "",
                    "jugador": "Andrés Saavedra",
                    "penal": false
                }
            ],
            "info": {
                "amarillas": [],
                "rojas_directas": []
            },
            "logo": "cacu.png"
        },
        "visitante": {
            "nombre": {
                "completo": "UNIÓN SOCIAL DE HERSILIA",
                "corto": "USdH"
            },
            "goles": [],
            "info": {
                "amarillas": [],
                "rojas_directas": []
            },
            "logo": "hersilia.png"
        },
        "fecha": "18/08/2024 - 16:00hs",
        "estado": "jugando",
        "contexto": []
    },
        
    {
        "local": {
            "nombre": {
                "completo": "UNION SAN GUILLERMO",
                "corto": "UCYD"
            },
            "goles": [
                {
                    "min": "",
                    "jugador": "Rafael Nicola",
                    "penal": false
                }
            ],
            "info": {
                "amarillas": [],
                "rojas_directas": []
            },
            "logo": "ucyd.png"
        },
        "visitante": {
            "nombre": {
                "completo": "ATL. TOSTADO",
                "corto": "CAT"
            },
            "goles": [
                {
                    "min": "",
                    "jugador": "Demaria",
                    "penal": false
                },
                {
                    "min": "",
                    "jugador": "Marcos Mantovani",
                    "penal": false
                },
                {
                    "min": "",
                    "jugador": "Brian Ocampo",
                    "penal": true
                }
            ],
            "info": {
                "amarillas": [],
                "rojas_directas": []
            },
            "logo": "cat.png"
        },
        "fecha": "18/08/2024 - 16:00hs",
        "estado": "jugando",
        "contexto": []
    },

    
    {
        "local": {
            "nombre": {
                "completo": "UNION Y JUVENTUD (B)",
                "corto": "UJB"
            },
            "goles": [            ],
            "info": {
                "amarillas": [],
                "rojas_directas": []
            },
            "logo": "bandera.png"
        },
        "visitante": {
            "nombre": {
                "completo": "CENTRAL ARG. OLÍMPICO",
                "corto": "CCAO"
            },
            "goles": [

            ],
            "info": {
                "amarillas": [],
                "rojas_directas": []
            },
            "logo": "ccao.png"
        },
        "fecha": "18/08/2024 - 17:00hs",
        "estado": "jugando",
        "contexto": []
    },



    {
        "local": {
            "nombre": {
                "completo": "ATL. SELVA",
                "corto": "CAS"
            },
            "goles": [            ],
            "info": {
                "amarillas": [],
                "rojas_directas": []
            },
            "logo": "cas.png"
        },
        "visitante": {
            "nombre": {
                "completo": "SAN LORENZO (A)",
                "corto": "CSLA"
            },
            "goles": [
            ],
            "info": {
                "amarillas": [],
                "rojas_directas": []
            },
            "logo": "ambro.png"
        },
        "fecha": "18/08/2024 - 19:00hs",
        "estado": "Por jugar",
        "contexto": []
    }
    


]
